{
    "configuration": {
        "status": "Success",
        "update": "2025-06-19 22:24:29.047800",
        "failure": "2025-06-16 11:05:38.423812",
        "runtime": "2025-06-19 22:24:29.047800",
        "duration": "2.730499s",
        "success": "2025-06-19 22:24:29.047800"
    },
    "operational_data": {
        "status": "Success",
        "update": "2025-06-19 22:24:31.879164",
        "failure": "Never",
        "runtime": "2025-06-19 22:24:31.879164",
        "duration": "5.159744s",
        "success": "2025-06-19 22:24:31.879164"
    }
}