{
    "configuration": {
        "status": "Success",
        "update": "2022-12-07 14:38:17.218344",
        "failure": "2022-04-13 15:59:28.944444",
        "runtime": "2022-12-07 14:38:17.218344",
        "duration": "2.093764s"
    },
    "operational_data": {
        "status": "Success",
        "update": "2022-12-07 14:38:19.367834",
        "failure": "2022-04-13 15:59:32.307044",
        "runtime": "2022-12-07 14:38:19.367834",
        "duration": "3.991951s"
    },
    "specialized_data": {
        "status": "Success",
        "update": "2022-02-14 10:13:39.034416",
        "failure": "Never",
        "runtime": "2022-02-14 10:13:39.034416",
        "duration": "3.775398s"
    }
}